moontex/__init__.py
moontex/moontex.py
moontex-1.0.1.dist-info/licenses/LICENSE
moontex-1.0.1.dist-info/METADATA
moontex-1.0.1.dist-info/WHEEL
moontex-1.0.1.dist-info/top_level.txt
moontex-1.0.1.dist-info/RECORD
