Metadata-Version: 2.4
Name: moontex
Version: 1.0.1
Summary: MoonTex is a noise-based texture generator that creates realistic grayscale moon phase images.
Author: Brianna Ladson
License: MIT
Keywords: moon,moon phases,lunar,crater texture,texture generator,procedural generation,procedural textures,simplex noise,noise generator,2d noise,game assets,game development
Classifier: Development Status :: 4 - Beta
Classifier: Intended Audience :: Developers
Classifier: Programming Language :: Python :: 3
Classifier: License :: OSI Approved :: MIT License
Classifier: Operating System :: OS Independent
Classifier: Topic :: Games/Entertainment
Classifier: Topic :: Software Development :: Libraries :: Python Modules
Requires-Python: >=3.7
License-File: LICENSE
Requires-Dist: Pillow
Requires-Dist: noise
Dynamic: license-file
